{
    "type": "main",
    "main": {
        "title": "Auja example",
        "authenticated": false,
        "debug": true,
        "colors": {
            "main": "#22bcb9",
            "secondary": "#E7EFEF"
        },
        "user": {
            "name": "Joris Blaak"
        },
        "buttons": [
            {
                "title": "Logout",
                "target": "#logout"
            }
        ],
        "menu": [
            {
                "title": "Clubs",
                "icon": "group",
                "target": "example/clubs_menu.json"
            },
            {
                "title": "Clubs (resource)",
                "icon": "group",
                "target": "clubs/menu"
            }
        ],
        "routes": [
            {
                "type": "rest",
                "resource": "clubs",
                "endpoint": "clubs"
            }
        ],
        "authentication": false
    }
}